[{"uid": 13990, "odi_type": "daynight", "winner_id": "New-Zealand", "status": "New Zealand won by 34 runs (D/L method)", "toss_winner_id": "New-Zealand", "toss_choice": "bowl", "match_tied": 0, "series_name": "England tour of New Zealand", "series_id": 300413, "match_id": 300441, "match_date": "2008-02-23 01:00:00+00:00", "stadium_id": 152, "stadium_obj_id": 58812, "stadium_name": "AMI Stadium", "stadium_place_id": 824, "stadium_place": "Christchurch", "stadium_country_id": 5, "home_team_id": 1, "home_team_score": "242/7", "home_team_score_info": null, "home_team_innings": 1, "away_team_id": 5, "away_team_score": "213/6", "away_team_score_info": "37/37 ov, target 180", "away_team_innings": 2, "home_team": "England", "home_team_runs": 242, "home_team_wickets": 7, "home_team_overs_played": 50, "home_team_balls_played": 300, "away_team": "New-Zealand", "away_team_runs": 213, "away_team_wickets": 6, "away_team_overs_played": 37, "away_team_balls_played": 222}, {"uid": 13989, "odi_type": "day", "winner_id": null, "status": "Match tied", "toss_winner_id": "New-Zealand", "toss_choice": "bowl", "match_tied": 1, "series_name": "England tour of New Zealand", "series_id": 300413, "match_id": 300440, "match_date": "2008-02-19 22:00:00+00:00", "stadium_id": 453, "stadium_obj_id": 58857, "stadium_name": "McLean Park", "stadium_place_id": 836, "stadium_place": "Napier", "stadium_country_id": 5, "home_team_id": 1, "home_team_score": "340/6", "home_team_score_info": null, "home_team_innings": 1, "away_team_id": 5, "away_team_score": "340/7", "away_team_score_info": "50 ov, target 341", "away_team_innings": 2, "home_team": "England", "home_team_runs": 340, "home_team_wickets": 6, "home_team_overs_played": 50, "home_team_balls_played": 300, "away_team": "New-Zealand", "away_team_runs": 340, "away_team_wickets": 7, "away_team_overs_played": 50, "away_team_balls_played": 300}, {"uid": 13988, "odi_type": "daynight", "winner_id": "England", "status": "England won by 6 wickets (with 18 balls remaining) (D/L method)", "toss_winner_id": "England", "toss_choice": "bowl", "match_tied": 0, "series_name": "England tour of New Zealand", "series_id": 300413, "match_id": 300439, "match_date": "2008-02-15 01:00:00+00:00", "stadium_id": 283, "stadium_obj_id": 58792, "stadium_name": "Eden Park", "stadium_place_id": 822, "stadium_place": "Auckland", "stadium_country_id": 5, "home_team_id": 5, "home_team_score": "234/9", "home_team_score_info": null, "home_team_innings": 1, "away_team_id": 1, "away_team_score": "229/4", "away_team_score_info": "44/47 ov", "away_team_innings": 2, "home_team": "New-Zealand", "home_team_runs": 234, "home_team_wickets": 9, "home_team_overs_played": 50, "home_team_balls_played": 300, "away_team": "England", "away_team_runs": 229, "away_team_wickets": 4, "away_team_overs_played": 44, "away_team_balls_played": 264}, {"uid": 13987, "odi_type": "daynight", "winner_id": "New-Zealand", "status": "New Zealand won by 10 wickets (with 107 balls remaining) (D/L method)", "toss_winner_id": "New-Zealand", "toss_choice": "bowl", "match_tied": 0, "series_name": "England tour of New Zealand", "series_id": 300413, "match_id": 300438, "match_date": "2008-02-12 01:00:00+00:00", "stadium_id": 504, "stadium_obj_id": 58831, "stadium_name": "Seddon Park", "stadium_place_id": 827, "stadium_place": "Hamilton", "stadium_country_id": 5, "home_team_id": 1, "home_team_score": "158", "home_team_score_info": null, "home_team_innings": 1, "away_team_id": 5, "away_team_score": "165/0", "away_team_score_info": "18.1/36 ov", "away_team_innings": 2, "home_team": "England", "home_team_runs": 158, "home_team_wickets": 10, "home_team_overs_played": 35.1, "home_team_balls_played": 211, "away_team": "New-Zealand", "away_team_runs": 165, "away_team_wickets": 0, "away_team_overs_played": 18.1, "away_team_balls_played": 109}, {"uid": 13986, "odi_type": "daynight", "winner_id": "New-Zealand", "status": "New Zealand won by 6 wickets (with 120 balls remaining)", "toss_winner_id": "England", "toss_choice": "bat", "match_tied": 0, "series_name": "England tour of New Zealand", "series_id": 300413, "match_id": 300437, "match_date": "2008-02-09 01:00:00+00:00", "stadium_id": 1166, "stadium_obj_id": 58899, "stadium_name": "Westpac Stadium", "stadium_place_id": 851, "stadium_place": "Wellington", "stadium_country_id": 5, "home_team_id": 1, "home_team_score": "130", "home_team_score_info": null, "home_team_innings": 1, "away_team_id": 5, "away_team_score": "131/4", "away_team_score_info": "30/50 ov", "away_team_innings": 2, "home_team": "England", "home_team_runs": 130, "home_team_wickets": 10, "home_team_overs_played": 49.4, "home_team_balls_played": 298, "away_team": "New-Zealand", "away_team_runs": 131, "away_team_wickets": 4, "away_team_overs_played": 30, "away_team_balls_played": 180}, {"uid": 13593, "odi_type": "day", "winner_id": "New-Zealand", "status": "New Zealand won by 51 runs", "toss_winner_id": "England", "toss_choice": "bowl", "match_tied": 0, "series_name": "New Zealand tour of England and Scotland", "series_id": 296889, "match_id": 296908, "match_date": "2008-06-28 09:45:00+00:00", "stadium_id": 10, "stadium_obj_id": 57129, "stadium_name": "Lord's", "stadium_place_id": 224, "stadium_place": "London", "stadium_country_id": 1, "home_team_id": 5, "home_team_score": "266/5", "home_team_score_info": null, "home_team_innings": 1, "away_team_id": 1, "away_team_score": "215", "away_team_score_info": "47.5/50 ov, target 267", "away_team_innings": 2, "home_team": "New-Zealand", "home_team_runs": 266, "home_team_wickets": 5, "home_team_overs_played": 50, "home_team_balls_played": 300, "away_team": "England", "away_team_runs": 215, "away_team_wickets": 10, "away_team_overs_played": 47.5, "away_team_balls_played": 287}, {"uid": 13592, "odi_type": "day", "winner_id": "New-Zealand", "status": "New Zealand won by 1 wicket", "toss_winner_id": "New-Zealand", "toss_choice": "bowl", "match_tied": 0, "series_name": "New Zealand tour of England and Scotland", "series_id": 296889, "match_id": 296907, "match_date": "2008-06-25 10:45:00+00:00", "stadium_id": 45, "stadium_obj_id": 57127, "stadium_name": "Kennington Oval", "stadium_place_id": 224, "stadium_place": "London", "stadium_country_id": 1, "home_team_id": 1, "home_team_score": "245", "home_team_score_info": null, "home_team_innings": 1, "away_team_id": 5, "away_team_score": "246/9", "away_team_score_info": "50 ov", "away_team_innings": 2, "home_team": "England", "home_team_runs": 245, "home_team_wickets": 10, "home_team_overs_played": 49.4, "home_team_balls_played": 298, "away_team": "New-Zealand", "away_team_runs": 246, "away_team_wickets": 9, "away_team_overs_played": 50, "away_team_balls_played": 300}, {"uid": 13591, "odi_type": "day", "winner_id": "New-Zealand", "status": "New Zealand won by 22 runs", "toss_winner_id": "England", "toss_choice": "bowl", "match_tied": 0, "series_name": "New Zealand tour of England and Scotland", "series_id": 296889, "match_id": 296906, "match_date": "2008-06-21 09:45:00+00:00", "stadium_id": 176, "stadium_obj_id": 56831, "stadium_name": "County Ground", "stadium_place_id": 116, "stadium_place": "Bristol", "stadium_country_id": 1, "home_team_id": 5, "home_team_score": "182", "home_team_score_info": null, "home_team_innings": 1, "away_team_id": 1, "away_team_score": "160", "away_team_score_info": "46.2/50 ov, target 183", "away_team_innings": 2, "home_team": "New-Zealand", "home_team_runs": 182, "home_team_wickets": 10, "home_team_overs_played": 50, "home_team_balls_played": 300, "away_team": "England", "away_team_runs": 160, "away_team_wickets": 10, "away_team_overs_played": 46.2, "away_team_balls_played": 278}, {"uid": 13589, "odi_type": "day", "winner_id": "England", "status": "England won by 114 runs", "toss_winner_id": "New-Zealand", "toss_choice": "bowl", "match_tied": 0, "series_name": "New Zealand tour of England and Scotland", "series_id": 296889, "match_id": 296904, "match_date": "2008-06-15 09:45:00+00:00", "stadium_id": 1039, "stadium_obj_id": 56901, "stadium_name": "Riverside Ground", "stadium_place_id": 134, "stadium_place": "Chester-le-Street", "stadium_country_id": 1, "home_team_id": 1, "home_team_score": "307/5", "home_team_score_info": null, "home_team_innings": 1, "away_team_id": 5, "away_team_score": "193", "away_team_score_info": "42.5/50 ov, target 308", "away_team_innings": 2, "home_team": "England", "home_team_runs": 307, "home_team_wickets": 5, "home_team_overs_played": 50, "home_team_balls_played": 300, "away_team": "New-Zealand", "away_team_runs": 193, "away_team_wickets": 10, "away_team_overs_played": 42.5, "away_team_balls_played": 257}, {"uid": 13602, "odi_type": "day", "winner_id": "England", "status": "England won by 7 wickets (with 14 balls remaining) (D/L method)", "toss_winner_id": "England", "toss_choice": "bowl", "match_tied": 0, "series_name": "South Africa tour of England", "series_id": 296890, "match_id": 296917, "match_date": "2008-08-31 09:45:00+00:00", "stadium_id": 10, "stadium_obj_id": 57129, "stadium_name": "Lord's", "stadium_place_id": 224, "stadium_place": "London", "stadium_country_id": 1, "home_team_id": 3, "home_team_score": "183/6", "home_team_score_info": null, "home_team_innings": 1, "away_team_id": 1, "away_team_score": "137/3", "away_team_score_info": "17.4/20 ov", "away_team_innings": 2, "home_team": "South-Africa", "home_team_runs": 183, "home_team_wickets": 6, "home_team_overs_played": 32.1, "home_team_balls_played": 193, "away_team": "England", "away_team_runs": 137, "away_team_wickets": 3, "away_team_overs_played": 17.4, "away_team_balls_played": 106}, {"uid": 13601, "odi_type": "day", "winner_id": "England", "status": "England won by 126 runs", "toss_winner_id": "South-Africa", "toss_choice": "bowl", "match_tied": 0, "series_name": "South Africa tour of England", "series_id": 296890, "match_id": 296916, "match_date": "2008-08-29 09:45:00+00:00", "stadium_id": 45, "stadium_obj_id": 57127, "stadium_name": "Kennington Oval", "stadium_place_id": 224, "stadium_place": "London", "stadium_country_id": 1, "home_team_id": 1, "home_team_score": "296/7", "home_team_score_info": null, "home_team_innings": 1, "away_team_id": 3, "away_team_score": "170", "away_team_score_info": "42.4/50 ov, target 297", "away_team_innings": 2, "home_team": "England", "home_team_runs": 296, "home_team_wickets": 7, "home_team_overs_played": 50, "home_team_balls_played": 300, "away_team": "South-Africa", "away_team_runs": 170, "away_team_wickets": 10, "away_team_overs_played": 42.4, "away_team_balls_played": 256}, {"uid": 13600, "odi_type": "daynight", "winner_id": "England", "status": "England won by 10 wickets (with 215 balls remaining)", "toss_winner_id": "South-Africa", "toss_choice": "bat", "match_tied": 0, "series_name": "South Africa tour of England", "series_id": 296890, "match_id": 296915, "match_date": "2008-08-26 13:30:00+00:00", "stadium_id": 34, "stadium_obj_id": 57219, "stadium_name": "Trent Bridge", "stadium_place_id": 254, "stadium_place": "Nottingham", "stadium_country_id": 1, "home_team_id": 3, "home_team_score": "83", "home_team_score_info": null, "home_team_innings": 1, "away_team_id": 1, "away_team_score": "85/0", "away_team_score_info": "14.1/50 ov, target 84", "away_team_innings": 2, "home_team": "South-Africa", "home_team_runs": 83, "home_team_wickets": 10, "home_team_overs_played": 23, "home_team_balls_played": 138, "away_team": "England", "away_team_runs": 85, "away_team_wickets": 0, "away_team_overs_played": 14.1, "away_team_balls_played": 85}, {"uid": 13599, "odi_type": "daynight", "winner_id": "England", "status": "England won by 20 runs", "toss_winner_id": "England", "toss_choice": "bat", "match_tied": 0, "series_name": "South Africa tour of England", "series_id": 296890, "match_id": 296914, "match_date": "2008-08-22 13:30:00+00:00", "stadium_id": 179, "stadium_obj_id": 57092, "stadium_name": "Headingley", "stadium_place_id": 213, "stadium_place": "Leeds", "stadium_country_id": 1, "home_team_id": 1, "home_team_score": "275/4", "home_team_score_info": null, "home_team_innings": 1, "away_team_id": 3, "away_team_score": "255", "away_team_score_info": "49.4/50 ov, target 276", "away_team_innings": 2, "home_team": "England", "home_team_runs": 275, "home_team_wickets": 4, "home_team_overs_played": 50, "home_team_balls_played": 300, "away_team": "South-Africa", "away_team_runs": 255, "away_team_wickets": 10, "away_team_overs_played": 49.4, "away_team_balls_played": 298}, {"uid": 20761, "odi_type": "daynight", "winner_id": "India", "status": "India won by 6 wickets (with 38 balls remaining)", "toss_winner_id": "India", "toss_choice": "bowl", "match_tied": 0, "series_name": "England tour of India", "series_id": 361035, "match_id": 361047, "match_date": "2008-11-26 09:00:00+00:00", "stadium_id": 442, "stadium_obj_id": 58027, "stadium_name": "Barabati Stadium", "stadium_place_id": 581, "stadium_place": "Cuttack", "stadium_country_id": 6, "home_team_id": 1, "home_team_score": "270/4", "home_team_score_info": null, "home_team_innings": 1, "away_team_id": 6, "away_team_score": "273/4", "away_team_score_info": "43.4/50 ov, target 271", "away_team_innings": 2, "home_team": "England", "home_team_runs": 270, "home_team_wickets": 4, "home_team_overs_played": 50, "home_team_balls_played": 300, "away_team": "India", "away_team_runs": 273, "away_team_wickets": 4, "away_team_overs_played": 43.4, "away_team_balls_played": 262}, {"uid": 20760, "odi_type": "daynight", "winner_id": "India", "status": "India won by 19 runs (D/L method)", "toss_winner_id": "England", "toss_choice": "bowl", "match_tied": 0, "series_name": "England tour of India", "series_id": 361035, "match_id": 361046, "match_date": "2008-11-23 14:00:00+00:00", "stadium_id": 683, "stadium_obj_id": 57897, "stadium_name": "M.Chinnaswamy Stadium", "stadium_place_id": 549, "stadium_place": "Bengaluru", "stadium_country_id": 6, "home_team_id": 6, "home_team_score": "166/4", "home_team_score_info": null, "home_team_innings": 1, "away_team_id": 1, "away_team_score": "178/8", "away_team_score_info": "22/22 ov, target 198", "away_team_innings": 2, "home_team": "India", "home_team_runs": 166, "home_team_wickets": 4, "home_team_overs_played": 22, "home_team_balls_played": 132, "away_team": "England", "away_team_runs": 178, "away_team_wickets": 8, "away_team_overs_played": 22, "away_team_balls_played": 132}, {"uid": 20759, "odi_type": "day", "winner_id": "India", "status": "India won by 16 runs (D/L method)", "toss_winner_id": "England", "toss_choice": "bat", "match_tied": 0, "series_name": "England tour of India", "series_id": 361035, "match_id": 361045, "match_date": "2008-11-20 03:30:00+00:00", "stadium_id": 419, "stadium_obj_id": 58204, "stadium_name": "Green Park", "stadium_place_id": 630, "stadium_place": "Kanpur", "stadium_country_id": 6, "home_team_id": 1, "home_team_score": "240", "home_team_score_info": null, "home_team_innings": 1, "away_team_id": 6, "away_team_score": "198/5", "away_team_score_info": "40/40 ov, target 183", "away_team_innings": 2, "home_team": "England", "home_team_runs": 240, "home_team_wickets": 10, "home_team_overs_played": 48.4, "home_team_balls_played": 292, "away_team": "India", "away_team_runs": 198, "away_team_wickets": 5, "away_team_overs_played": 40, "away_team_balls_played": 240}, {"uid": 20758, "odi_type": "day", "winner_id": "India", "status": "India won by 54 runs", "toss_winner_id": "India", "toss_choice": "bat", "match_tied": 0, "series_name": "England tour of India", "series_id": 361035, "match_id": 361044, "match_date": "2008-11-17 03:30:00+00:00", "stadium_id": 1055, "stadium_obj_id": 58150, "stadium_name": "Holkar Cricket Stadium", "stadium_place_id": 615, "stadium_place": "Indore", "stadium_country_id": 6, "home_team_id": 6, "home_team_score": "292/9", "home_team_score_info": null, "home_team_innings": 1, "away_team_id": 1, "away_team_score": "238", "away_team_score_info": "47/50 ov, target 293", "away_team_innings": 2, "home_team": "India", "home_team_runs": 292, "home_team_wickets": 9, "home_team_overs_played": 50, "home_team_balls_played": 300, "away_team": "England", "away_team_runs": 238, "away_team_wickets": 10, "away_team_overs_played": 47, "away_team_balls_played": 282}, {"uid": 20757, "odi_type": "day", "winner_id": "India", "status": "India won by 158 runs", "toss_winner_id": "England", "toss_choice": "bowl", "match_tied": 0, "series_name": "England tour of India", "series_id": 361035, "match_id": 361043, "match_date": "2008-11-14 03:30:00+00:00", "stadium_id": 385, "stadium_obj_id": 58401, "stadium_name": "Madhavrao Scindia Cricket Ground", "stadium_place_id": 689, "stadium_place": "Rajkot", "stadium_country_id": 6, "home_team_id": 6, "home_team_score": "387/5", "home_team_score_info": null, "home_team_innings": 1, "away_team_id": 1, "away_team_score": "229", "away_team_score_info": "37.4/50 ov, target 388", "away_team_innings": 2, "home_team": "India", "home_team_runs": 387, "home_team_wickets": 5, "home_team_overs_played": 50, "home_team_balls_played": 300, "away_team": "England", "away_team_runs": 229, "away_team_wickets": 10, "away_team_overs_played": 37.4, "away_team_balls_played": 226}, {"uid": 13451, "odi_type": "daynight", "winner_id": "Sri-Lanka", "status": "Sri Lanka won by 13 runs", "toss_winner_id": "Sri-Lanka", "toss_choice": "bat", "match_tied": 0, "series_name": "Commonwealth Bank Series", "series_id": 291340, "match_id": 291370, "match_date": "2008-02-29 03:15:00+00:00", "stadium_id": 61, "stadium_obj_id": 56441, "stadium_name": "Melbourne Cricket Ground", "stadium_place_id": 25, "stadium_place": "Melbourne", "stadium_country_id": 2, "home_team_id": 8, "home_team_score": "221", "home_team_score_info": null, "home_team_innings": 1, "away_team_id": 2, "away_team_score": "208", "away_team_score_info": "48.1/50 ov, target 222", "away_team_innings": 2, "home_team": "Sri-Lanka", "home_team_runs": 221, "home_team_wickets": 10, "home_team_overs_played": 50, "home_team_balls_played": 300, "away_team": "Australia", "away_team_runs": 208, "away_team_wickets": 10, "away_team_overs_played": 48.1, "away_team_balls_played": 289}, {"uid": 13449, "odi_type": "daynight", "winner_id": "Australia", "status": "Australia won by 18 runs", "toss_winner_id": "Australia", "toss_choice": "bat", "match_tied": 0, "series_name": "Commonwealth Bank Series", "series_id": 291340, "match_id": 291368, "match_date": "2008-02-24 03:15:00+00:00", "stadium_id": 132, "stadium_obj_id": 56544, "stadium_name": "Sydney Cricket Ground", "stadium_place_id": 29, "stadium_place": "Sydney", "stadium_country_id": 2, "home_team_id": 2, "home_team_score": "317/7", "home_team_score_info": null, "home_team_innings": 1, "away_team_id": 6, "away_team_score": "299", "away_team_score_info": "49.1/50 ov, target 318", "away_team_innings": 2, "home_team": "Australia", "home_team_runs": 317, "home_team_wickets": 7, "home_team_overs_played": 50, "home_team_balls_played": 300, "away_team": "India", "away_team_runs": 299, "away_team_wickets": 10, "away_team_overs_played": 49.1, "away_team_balls_played": 295}, {"uid": 13448, "odi_type": "daynight", "winner_id": "Australia", "status": "Australia won by 24 runs (D/L method)", "toss_winner_id": "Sri-Lanka", "toss_choice": "bowl", "match_tied": 0, "series_name": "Commonwealth Bank Series", "series_id": 291340, "match_id": 291367, "match_date": "2008-02-22 03:15:00+00:00", "stadium_id": 61, "stadium_obj_id": 56441, "stadium_name": "Melbourne Cricket Ground", "stadium_place_id": 25, "stadium_place": "Melbourne", "stadium_country_id": 2, "home_team_id": 2, "home_team_score": "184/7", "home_team_score_info": null, "home_team_innings": 1, "away_team_id": 8, "away_team_score": "77/4", "away_team_score_info": "29.3/29.3 ov, target 102", "away_team_innings": 2, "home_team": "Australia", "home_team_runs": 184, "home_team_wickets": 7, "home_team_overs_played": 50, "home_team_balls_played": 300, "away_team": "Sri-Lanka", "away_team_runs": 77, "away_team_wickets": 4, "away_team_overs_played": 29.3, "away_team_balls_played": 177}, {"uid": 13446, "odi_type": "daynight", "winner_id": "Australia", "status": "Australia won by 50 runs", "toss_winner_id": "Australia", "toss_choice": "bat", "match_tied": 0, "series_name": "Commonwealth Bank Series", "series_id": 291340, "match_id": 291365, "match_date": "2008-02-17 03:15:00+00:00", "stadium_id": 131, "stadium_obj_id": 56293, "stadium_name": "Adelaide Oval", "stadium_place_id": 2, "stadium_place": "Adelaide", "stadium_country_id": 2, "home_team_id": 2, "home_team_score": "203/9", "home_team_score_info": null, "home_team_innings": 1, "away_team_id": 6, "away_team_score": "153", "away_team_score_info": "41.2/50 ov, target 204", "away_team_innings": 2, "home_team": "Australia", "home_team_runs": 203, "home_team_wickets": 9, "home_team_overs_played": 50, "home_team_balls_played": 300, "away_team": "India", "away_team_runs": 153, "away_team_wickets": 10, "away_team_overs_played": 41.2, "away_team_balls_played": 248}, {"uid": 13445, "odi_type": "daynight", "winner_id": "Australia", "status": "Australia won by 63 runs", "toss_winner_id": "Australia", "toss_choice": "bat", "match_tied": 0, "series_name": "Commonwealth Bank Series", "series_id": 291340, "match_id": 291364, "match_date": "2008-02-15 04:30:00+00:00", "stadium_id": 213, "stadium_obj_id": 56490, "stadium_name": "W.A.C.A. Ground", "stadium_place_id": 27, "stadium_place": "Perth", "stadium_country_id": 2, "home_team_id": 2, "home_team_score": "236", "home_team_score_info": null, "home_team_innings": 1, "away_team_id": 8, "away_team_score": "173", "away_team_score_info": "45.3/50 ov, target 237", "away_team_innings": 2, "home_team": "Australia", "home_team_runs": 236, "home_team_wickets": 10, "home_team_overs_played": 49.4, "home_team_balls_played": 298, "away_team": "Sri-Lanka", "away_team_runs": 173, "away_team_wickets": 10, "away_team_overs_played": 45.3, "away_team_balls_played": 273}, {"uid": 13443, "odi_type": "daynight", "winner_id": "India", "status": "India won by 5 wickets (with 25 balls remaining)", "toss_winner_id": "Australia", "toss_choice": "bat", "match_tied": 0, "series_name": "Commonwealth Bank Series", "series_id": 291340, "match_id": 291362, "match_date": "2008-02-10 03:15:00+00:00", "stadium_id": 61, "stadium_obj_id": 56441, "stadium_name": "Melbourne Cricket Ground", "stadium_place_id": 25, "stadium_place": "Melbourne", "stadium_country_id": 2, "home_team_id": 2, "home_team_score": "159", "home_team_score_info": null, "home_team_innings": 1, "away_team_id": 6, "away_team_score": "160/5", "away_team_score_info": "45.5/50 ov", "away_team_innings": 2, "home_team": "Australia", "home_team_runs": 159, "home_team_wickets": 10, "home_team_overs_played": 43.1, "home_team_balls_played": 259, "away_team": "India", "away_team_runs": 160, "away_team_wickets": 5, "away_team_overs_played": 45.5, "away_team_balls_played": 275}, {"uid": 13442, "odi_type": "daynight", "winner_id": "Australia", "status": "Australia won by 128 runs", "toss_winner_id": "Australia", "toss_choice": "bat", "match_tied": 0, "series_name": "Commonwealth Bank Series", "series_id": 291340, "match_id": 291361, "match_date": "2008-02-08 03:15:00+00:00", "stadium_id": 132, "stadium_obj_id": 56544, "stadium_name": "Sydney Cricket Ground", "stadium_place_id": 29, "stadium_place": "Sydney", "stadium_country_id": 2, "home_team_id": 2, "home_team_score": "253/6", "home_team_score_info": null, "home_team_innings": 1, "away_team_id": 8, "away_team_score": "125", "away_team_score_info": "31.3/50 ov, target 254", "away_team_innings": 2, "home_team": "Australia", "home_team_runs": 253, "home_team_wickets": 6, "home_team_overs_played": 50, "home_team_balls_played": 300, "away_team": "Sri-Lanka", "away_team_runs": 125, "away_team_wickets": 10, "away_team_overs_played": 31.3, "away_team_balls_played": 189}, {"uid": 13453, "odi_type": "daynight", "winner_id": "India", "status": "India won by 9 runs", "toss_winner_id": "India", "toss_choice": "bat", "match_tied": 0, "series_name": "Commonwealth Bank Series", "series_id": 291340, "match_id": 291372, "match_date": "2008-03-04 03:15:00+00:00", "stadium_id": 209, "stadium_obj_id": 56336, "stadium_name": "Brisbane Cricket Ground", "stadium_place_id": 8, "stadium_place": "Brisbane", "stadium_country_id": 2, "home_team_id": 6, "home_team_score": "258/9", "home_team_score_info": null, "home_team_innings": 1, "away_team_id": 2, "away_team_score": "249", "away_team_score_info": "49.4/50 ov, target 259", "away_team_innings": 2, "home_team": "India", "home_team_runs": 258, "home_team_wickets": 9, "home_team_overs_played": 50, "home_team_balls_played": 300, "away_team": "Australia", "away_team_runs": 249, "away_team_wickets": 10, "away_team_overs_played": 49.4, "away_team_balls_played": 298}, {"uid": 13452, "odi_type": "daynight", "winner_id": "India", "status": "India won by 6 wickets (with 25 balls remaining)", "toss_winner_id": "Australia", "toss_choice": "bat", "match_tied": 0, "series_name": "Commonwealth Bank Series", "series_id": 291340, "match_id": 291371, "match_date": "2008-03-02 03:15:00+00:00", "stadium_id": 132, "stadium_obj_id": 56544, "stadium_name": "Sydney Cricket Ground", "stadium_place_id": 29, "stadium_place": "Sydney", "stadium_country_id": 2, "home_team_id": 2, "home_team_score": "239/8", "home_team_score_info": null, "home_team_innings": 1, "away_team_id": 6, "away_team_score": "242/4", "away_team_score_info": "45.5/50 ov, target 240", "away_team_innings": 2, "home_team": "Australia", "home_team_runs": 239, "home_team_wickets": 8, "home_team_overs_played": 50, "home_team_balls_played": 300, "away_team": "India", "away_team_runs": 242, "away_team_wickets": 4, "away_team_overs_played": 45.5, "away_team_balls_played": 275}, {"uid": 15732, "odi_type": "day", "winner_id": "Australia", "status": "Australia won by 7 wickets (with 57 balls remaining)", "toss_winner_id": "Australia", "toss_choice": "bowl", "match_tied": 0, "series_name": "Australia tour of West Indies", "series_id": 319125, "match_id": 319145, "match_date": "2008-06-29 13:30:00+00:00", "stadium_id": 1131, "stadium_obj_id": 59490, "stadium_name": "National Cricket Stadium", "stadium_place_id": 1008, "stadium_place": "St George's", "stadium_country_id": 4, "home_team_id": 4, "home_team_score": "223", "home_team_score_info": null, "home_team_innings": 1, "away_team_id": 2, "away_team_score": "227/3", "away_team_score_info": "40.3/50 ov, target 224", "away_team_innings": 2, "home_team": "West-Indies", "home_team_runs": 223, "home_team_wickets": 10, "home_team_overs_played": 48, "home_team_balls_played": 288, "away_team": "Australia", "away_team_runs": 227, "away_team_wickets": 3, "away_team_overs_played": 40.3, "away_team_balls_played": 243}, {"uid": 15731, "odi_type": "day", "winner_id": "Australia", "status": "Australia won by 63 runs (D/L method)", "toss_winner_id": "Australia", "toss_choice": "bat", "match_tied": 0, "series_name": "Australia tour of West Indies", "series_id": 319125, "match_id": 319144, "match_date": "2008-06-27 13:30:00+00:00", "stadium_id": 1131, "stadium_obj_id": 59490, "stadium_name": "National Cricket Stadium", "stadium_place_id": 1008, "stadium_place": "St George's", "stadium_country_id": 4, "home_team_id": 2, "home_team_score": "213/5", "home_team_score_info": null, "home_team_innings": 1, "away_team_id": 4, "away_team_score": "140/8", "away_team_score_info": "41/41 ov, target 204", "away_team_innings": 2, "home_team": "Australia", "home_team_runs": 213, "home_team_wickets": 5, "home_team_overs_played": 50, "home_team_balls_played": 300, "away_team": "West-Indies", "away_team_runs": 140, "away_team_wickets": 8, "away_team_overs_played": 41, "away_team_balls_played": 246}, {"uid": 15730, "odi_type": "day", "winner_id": "Australia", "status": "Australia won by 84 runs", "toss_winner_id": "West-Indies", "toss_choice": "bowl", "match_tied": 0, "series_name": "Australia tour of West Indies", "series_id": 319125, "match_id": 319143, "match_date": "2008-06-24 13:30:00+00:00", "stadium_id": 680, "stadium_obj_id": 59463, "stadium_name": "Arnos Vale Ground", "stadium_place_id": 997, "stadium_place": "Kingstown", "stadium_country_id": 4, "home_team_id": 2, "home_team_score": "273/8", "home_team_score_info": null, "home_team_innings": 1, "away_team_id": 4, "away_team_score": "189", "away_team_score_info": "39.5/50 ov, target 274", "away_team_innings": 2, "home_team": "Australia", "home_team_runs": 273, "home_team_wickets": 8, "home_team_overs_played": 50, "home_team_balls_played": 300, "away_team": "West-Indies", "away_team_runs": 189, "away_team_wickets": 10, "away_team_overs_played": 39.5, "away_team_balls_played": 239}, {"uid": 15734, "odi_type": "day", "winner_id": "Australia", "status": "Australia won by 169 runs", "toss_winner_id": "Australia", "toss_choice": "bat", "match_tied": 0, "series_name": "Australia tour of West Indies", "series_id": 319125, "match_id": 319147, "match_date": "2008-07-06 13:30:00+00:00", "stadium_id": 576, "stadium_obj_id": 59421, "stadium_name": "Warner Park", "stadium_place_id": 986, "stadium_place": "Basseterre", "stadium_country_id": 4, "home_team_id": 2, "home_team_score": "341/8", "home_team_score_info": null, "home_team_innings": 1, "away_team_id": 4, "away_team_score": "172", "away_team_score_info": "39.5/50 ov, target 342", "away_team_innings": 2, "home_team": "Australia", "home_team_runs": 341, "home_team_wickets": 8, "home_team_overs_played": 50, "home_team_balls_played": 300, "away_team": "West-Indies", "away_team_runs": 172, "away_team_wickets": 10, "away_team_overs_played": 39.5, "away_team_balls_played": 239}, {"uid": 15733, "odi_type": "day", "winner_id": "Australia", "status": "Australia won by 1 run", "toss_winner_id": "West-Indies", "toss_choice": "bowl", "match_tied": 0, "series_name": "Australia tour of West Indies", "series_id": 319125, "match_id": 319146, "match_date": "2008-07-04 13:30:00+00:00", "stadium_id": 576, "stadium_obj_id": 59421, "stadium_name": "Warner Park", "stadium_place_id": 986, "stadium_place": "Basseterre", "stadium_country_id": 4, "home_team_id": 2, "home_team_score": "282/8", "home_team_score_info": null, "home_team_innings": 1, "away_team_id": 4, "away_team_score": "281/6", "away_team_score_info": "50 ov, target 283", "away_team_innings": 2, "home_team": "Australia", "home_team_runs": 282, "home_team_wickets": 8, "home_team_overs_played": 50, "home_team_balls_played": 300, "away_team": "West-Indies", "away_team_runs": 281, "away_team_wickets": 6, "away_team_overs_played": 50, "away_team_balls_played": 300}, {"uid": 17889, "odi_type": "day", "winner_id": "Australia", "status": "Australia won by 180 runs", "toss_winner_id": "Bangladesh", "toss_choice": "bowl", "match_tied": 0, "series_name": "Bangladesh tour of Australia", "series_id": 336196, "match_id": 336201, "match_date": "2008-08-30 00:00:00+00:00", "stadium_id": 1155, "stadium_obj_id": 56390, "stadium_name": "TIO Stadium", "stadium_place_id": 16, "stadium_place": "Darwin", "stadium_country_id": 2, "home_team_id": 2, "home_team_score": "254/8", "home_team_score_info": null, "home_team_innings": 1, "away_team_id": 25, "away_team_score": "74", "away_team_score_info": "27.4/50 ov, target 255", "away_team_innings": 2, "home_team": "Australia", "home_team_runs": 254, "home_team_wickets": 8, "home_team_overs_played": 50, "home_team_balls_played": 300, "away_team": "Bangladesh", "away_team_runs": 74, "away_team_wickets": 10, "away_team_overs_played": 27.4, "away_team_balls_played": 166}, {"uid": 17891, "odi_type": "day", "winner_id": "Australia", "status": "Australia won by 73 runs", "toss_winner_id": "Australia", "toss_choice": "bat", "match_tied": 0, "series_name": "Bangladesh tour of Australia", "series_id": 336196, "match_id": 336204, "match_date": "2008-09-06 00:00:00+00:00", "stadium_id": 1155, "stadium_obj_id": 56390, "stadium_name": "TIO Stadium", "stadium_place_id": 16, "stadium_place": "Darwin", "stadium_country_id": 2, "home_team_id": 2, "home_team_score": "198/5", "home_team_score_info": null, "home_team_innings": 1, "away_team_id": 25, "away_team_score": "125", "away_team_score_info": "29.5/50 ov, target 199", "away_team_innings": 2, "home_team": "Australia", "home_team_runs": 198, "home_team_wickets": 5, "home_team_overs_played": 50, "home_team_balls_played": 300, "away_team": "Bangladesh", "away_team_runs": 125, "away_team_wickets": 9, "away_team_overs_played": 29.5, "away_team_balls_played": 179}, {"uid": 17890, "odi_type": "day", "winner_id": "Australia", "status": "Australia won by 8 wickets (with 164 balls remaining)", "toss_winner_id": "Bangladesh", "toss_choice": "bat", "match_tied": 0, "series_name": "Bangladesh tour of Australia", "series_id": 336196, "match_id": 336202, "match_date": "2008-09-03 00:00:00+00:00", "stadium_id": 1155, "stadium_obj_id": 56390, "stadium_name": "TIO Stadium", "stadium_place_id": 16, "stadium_place": "Darwin", "stadium_country_id": 2, "home_team_id": 25, "home_team_score": "117", "home_team_score_info": null, "home_team_innings": 1, "away_team_id": 2, "away_team_score": "118/2", "away_team_score_info": "22.4/50 ov", "away_team_innings": 2, "home_team": "Bangladesh", "home_team_runs": 117, "home_team_wickets": 10, "home_team_overs_played": 36.1, "home_team_balls_played": 217, "away_team": "Australia", "away_team_runs": 118, "away_team_wickets": 2, "away_team_overs_played": 22.4, "away_team_balls_played": 136}, {"uid": 13739, "odi_type": "day", "winner_id": "South-Africa", "status": "South Africa won by 7 wickets (with 8 balls remaining)", "toss_winner_id": "West-Indies", "toss_choice": "bat", "match_tied": 0, "series_name": "West Indies tour of Zimbabwe and South Africa", "series_id": 287844, "match_id": 298807, "match_date": "2008-01-27 08:00:00+00:00", "stadium_id": 173, "stadium_obj_id": 59159, "stadium_name": "St George's Park", "stadium_place_id": 911, "stadium_place": "Port Elizabeth", "stadium_country_id": 3, "home_team_id": 4, "home_team_score": "252/7", "home_team_score_info": null, "home_team_innings": 1, "away_team_id": 3, "away_team_score": "256/3", "away_team_score_info": "48.4/50 ov, target 253", "away_team_innings": 2, "home_team": "West-Indies", "home_team_runs": 252, "home_team_wickets": 7, "home_team_overs_played": 50, "home_team_balls_played": 300, "away_team": "South-Africa", "away_team_runs": 256, "away_team_wickets": 3, "away_team_overs_played": 48.4, "away_team_balls_played": 292}, {"uid": 13738, "odi_type": "daynight", "winner_id": "South-Africa", "status": "South Africa won by 86 runs", "toss_winner_id": "South-Africa", "toss_choice": "bat", "match_tied": 0, "series_name": "West Indies tour of Zimbabwe and South Africa", "series_id": 287844, "match_id": 298806, "match_date": "2008-01-25 12:30:00+00:00", "stadium_id": 174, "stadium_obj_id": 59068, "stadium_name": "Newlands", "stadium_place_id": 893, "stadium_place": "Cape Town", "stadium_country_id": 3, "home_team_id": 3, "home_team_score": "255/9", "home_team_score_info": null, "home_team_innings": 1, "away_team_id": 4, "away_team_score": "169", "away_team_score_info": "48.2/50 ov, target 256", "away_team_innings": 2, "home_team": "South-Africa", "home_team_runs": 255, "home_team_wickets": 9, "home_team_overs_played": 50, "home_team_balls_played": 300, "away_team": "West-Indies", "away_team_runs": 169, "away_team_wickets": 10, "away_team_overs_played": 48.2, "away_team_balls_played": 290}, {"uid": 13737, "odi_type": "day", "winner_id": "South-Africa", "status": "South Africa won by 6 wickets (with 12 balls remaining)", "toss_winner_id": "South-Africa", "toss_choice": "bowl", "match_tied": 0, "series_name": "West Indies tour of Zimbabwe and South Africa", "series_id": 287844, "match_id": 298805, "match_date": "2008-01-20 08:00:00+00:00", "stadium_id": 902, "stadium_obj_id": 59079, "stadium_name": "SuperSport Park", "stadium_place_id": 894, "stadium_place": "Centurion", "stadium_country_id": 3, "home_team_id": 4, "home_team_score": "175", "home_team_score_info": null, "home_team_innings": 1, "away_team_id": 3, "away_team_score": "176/4", "away_team_score_info": "34/36 ov", "away_team_innings": 2, "home_team": "West-Indies", "home_team_runs": 175, "home_team_wickets": 10, "home_team_overs_played": 35.5, "home_team_balls_played": 215, "away_team": "South-Africa", "away_team_runs": 176, "away_team_wickets": 4, "away_team_overs_played": 34, "away_team_balls_played": 204}, {"uid": 13741, "odi_type": "day", "winner_id": "South-Africa", "status": "South Africa won by 8 wickets (with 13 balls remaining) (D/L method)", "toss_winner_id": "South-Africa", "toss_choice": "bowl", "match_tied": 0, "series_name": "West Indies tour of Zimbabwe and South Africa", "series_id": 287844, "match_id": 298809, "match_date": "2008-02-03 08:00:00+00:00", "stadium_id": 508, "stadium_obj_id": 59120, "stadium_name": "The Wanderers Stadium", "stadium_place_id": 901, "stadium_place": "Johannesburg", "stadium_country_id": 3, "home_team_id": 4, "home_team_score": "295/7", "home_team_score_info": null, "home_team_innings": 1, "away_team_id": 3, "away_team_score": "211/2", "away_team_score_info": "28.5/31 ov", "away_team_innings": 2, "home_team": "West-Indies", "home_team_runs": 295, "home_team_wickets": 7, "home_team_overs_played": 50, "home_team_balls_played": 300, "away_team": "South-Africa", "away_team_runs": 211, "away_team_wickets": 2, "away_team_overs_played": 28.5, "away_team_balls_played": 173}, {"uid": 13740, "odi_type": "daynight", "winner_id": "South-Africa", "status": "South Africa won by 5 wickets (with 13 balls remaining)", "toss_winner_id": "West-Indies", "toss_choice": "bat", "match_tied": 0, "series_name": "West Indies tour of Zimbabwe and South Africa", "series_id": 287844, "match_id": 298808, "match_date": "2008-02-01 12:30:00+00:00", "stadium_id": 302, "stadium_obj_id": 59089, "stadium_name": "Kingsmead", "stadium_place_id": 897, "stadium_place": "Durban", "stadium_country_id": 3, "home_team_id": 4, "home_team_score": "263/9", "home_team_score_info": null, "home_team_innings": 1, "away_team_id": 3, "away_team_score": "266/5", "away_team_score_info": "47.5/50 ov, target 264", "away_team_innings": 2, "home_team": "West-Indies", "home_team_runs": 263, "home_team_wickets": 9, "home_team_overs_played": 50, "home_team_balls_played": 300, "away_team": "South-Africa", "away_team_runs": 266, "away_team_wickets": 5, "away_team_overs_played": 47.5, "away_team_balls_played": 287}, {"uid": 16429, "odi_type": "day", "winner_id": "South-Africa", "status": "South Africa won by 7 wickets (with 94 balls remaining)", "toss_winner_id": "Bangladesh", "toss_choice": "bat", "match_tied": 0, "series_name": "South Africa tour of Bangladesh", "series_id": 323940, "match_id": 323951, "match_date": "2008-03-14 03:30:00+00:00", "stadium_id": 2025, "stadium_obj_id": 236761, "stadium_name": "Shere Bangla National Stadium", "stadium_place_id": 58, "stadium_place": "Dhaka", "stadium_country_id": 25, "home_team_id": 25, "home_team_score": "143", "home_team_score_info": null, "home_team_innings": 1, "away_team_id": 3, "away_team_score": "147/3", "away_team_score_info": "34.2/50 ov, target 144", "away_team_innings": 2, "home_team": "Bangladesh", "home_team_runs": 143, "home_team_wickets": 10, "home_team_overs_played": 42.5, "home_team_balls_played": 257, "away_team": "South-Africa", "away_team_runs": 147, "away_team_wickets": 3, "away_team_overs_played": 34.2, "away_team_balls_played": 206}, {"uid": 16428, "odi_type": "day", "winner_id": "South-Africa", "status": "South Africa won by 7 wickets (with 11 balls remaining)", "toss_winner_id": "Bangladesh", "toss_choice": "bat", "match_tied": 0, "series_name": "South Africa tour of Bangladesh", "series_id": 323940, "match_id": 323950, "match_date": "2008-03-12 03:30:00+00:00", "stadium_id": 2025, "stadium_obj_id": 236761, "stadium_name": "Shere Bangla National Stadium", "stadium_place_id": 58, "stadium_place": "Dhaka", "stadium_country_id": 25, "home_team_id": 25, "home_team_score": "173", "home_team_score_info": null, "home_team_innings": 1, "away_team_id": 3, "away_team_score": "179/3", "away_team_score_info": "48.1/50 ov, target 174", "away_team_innings": 2, "home_team": "Bangladesh", "home_team_runs": 173, "home_team_wickets": 10, "home_team_overs_played": 48.2, "home_team_balls_played": 290, "away_team": "South-Africa", "away_team_runs": 179, "away_team_wickets": 3, "away_team_overs_played": 48.1, "away_team_balls_played": 289}, {"uid": 16427, "odi_type": "day", "winner_id": "South-Africa", "status": "South Africa won by 9 wickets (with 79 balls remaining)", "toss_winner_id": "Bangladesh", "toss_choice": "bat", "match_tied": 0, "series_name": "South Africa tour of Bangladesh", "series_id": 323940, "match_id": 323949, "match_date": "2008-03-09 03:30:00+00:00", "stadium_id": 1931, "stadium_obj_id": 56658, "stadium_name": "Zahur Ahmed Chowdhury Stadium", "stadium_place_id": 57, "stadium_place": "Chattogram", "stadium_country_id": 25, "home_team_id": 25, "home_team_score": "178", "home_team_score_info": null, "home_team_innings": 1, "away_team_id": 3, "away_team_score": "180/1", "away_team_score_info": "36.5/50 ov, target 179", "away_team_innings": 2, "home_team": "Bangladesh", "home_team_runs": 178, "home_team_wickets": 10, "home_team_overs_played": 48.2, "home_team_balls_played": 290, "away_team": "South-Africa", "away_team_runs": 180, "away_team_wickets": 1, "away_team_overs_played": 36.5, "away_team_balls_played": 221}, {"uid": 18304, "odi_type": "day", "winner_id": "South-Africa", "status": "South Africa won by 128 runs", "toss_winner_id": "Bangladesh", "toss_choice": "bowl", "match_tied": 0, "series_name": "Bangladesh tour of South Africa", "series_id": 350336, "match_id": 350349, "match_date": "2008-11-09 08:00:00+00:00", "stadium_id": 311, "stadium_obj_id": 59039, "stadium_name": "Willowmoore Park", "stadium_place_id": 887, "stadium_place": "Benoni", "stadium_country_id": 3, "home_team_id": 3, "home_team_score": "358/4", "home_team_score_info": null, "home_team_innings": 1, "away_team_id": 25, "away_team_score": "230", "away_team_score_info": "49.2/50 ov, target 359", "away_team_innings": 2, "home_team": "South-Africa", "home_team_runs": 358, "home_team_wickets": 4, "home_team_overs_played": 50, "home_team_balls_played": 300, "away_team": "Bangladesh", "away_team_runs": 230, "away_team_wickets": 10, "away_team_overs_played": 49.2, "away_team_balls_played": 296}, {"uid": 18303, "odi_type": "daynight", "winner_id": "South-Africa", "status": "South Africa won by 61 runs", "toss_winner_id": "South-Africa", "toss_choice": "bat", "match_tied": 0, "series_name": "Bangladesh tour of South Africa", "series_id": 350336, "match_id": 350348, "match_date": "2008-11-07 12:30:00+00:00", "stadium_id": 1367, "stadium_obj_id": 59172, "stadium_name": "Senwes Park", "stadium_place_id": 912, "stadium_place": "Potchefstroom", "stadium_country_id": 3, "home_team_id": 3, "home_team_score": "283/8", "home_team_score_info": null, "home_team_innings": 1, "away_team_id": 25, "away_team_score": "222", "away_team_score_info": "44.2/50 ov, target 284", "away_team_innings": 2, "home_team": "South-Africa", "home_team_runs": 283, "home_team_wickets": 8, "home_team_overs_played": 50, "home_team_balls_played": 300, "away_team": "Bangladesh", "away_team_runs": 222, "away_team_wickets": 10, "away_team_overs_played": 44.2, "away_team_balls_played": 266}, {"uid": 15722, "odi_type": "day", "winner_id": "West-Indies", "status": "West Indies won by 7 wickets (with 27 balls remaining) (D/L method)", "toss_winner_id": "West-Indies", "toss_choice": "bowl", "match_tied": 0, "series_name": "Sri Lanka tour of West Indies", "series_id": 319119, "match_id": 319135, "match_date": "2008-04-12 13:30:00+00:00", "stadium_id": 208, "stadium_obj_id": 59475, "stadium_name": "Queen's Park Oval", "stadium_place_id": 1002, "stadium_place": "Port of Spain", "stadium_country_id": 4, "home_team_id": 8, "home_team_score": "112/5", "home_team_score_info": null, "home_team_innings": 1, "away_team_id": 4, "away_team_score": "125/3", "away_team_score_info": "20.3/25 ov", "away_team_innings": 2, "home_team": "Sri-Lanka", "home_team_runs": 112, "home_team_wickets": 5, "home_team_overs_played": 30.3, "home_team_balls_played": 183, "away_team": "West-Indies", "away_team_runs": 125, "away_team_wickets": 3, "away_team_overs_played": 20.3, "away_team_balls_played": 123}, {"uid": 15721, "odi_type": "day", "winner_id": "West-Indies", "status": "West Indies won by 1 wicket", "toss_winner_id": "West-Indies", "toss_choice": "bowl", "match_tied": 0, "series_name": "Sri Lanka tour of West Indies", "series_id": 319119, "match_id": 319134, "match_date": "2008-04-10 13:30:00+00:00", "stadium_id": 208, "stadium_obj_id": 59475, "stadium_name": "Queen's Park Oval", "stadium_place_id": 1002, "stadium_place": "Port of Spain", "stadium_country_id": 4, "home_team_id": 8, "home_team_score": "235/7", "home_team_score_info": null, "home_team_innings": 1, "away_team_id": 4, "away_team_score": "236/9", "away_team_score_info": "50 ov", "away_team_innings": 2, "home_team": "Sri-Lanka", "home_team_runs": 235, "home_team_wickets": 7, "home_team_overs_played": 50, "home_team_balls_played": 300, "away_team": "West-Indies", "away_team_runs": 236, "away_team_wickets": 9, "away_team_overs_played": 50, "away_team_balls_played": 300}, {"uid": 23045, "odi_type": "daynight", "winner_id": "Pakistan", "status": "Pakistan won by 31 runs", "toss_winner_id": "Pakistan", "toss_choice": "bat", "match_tied": 0, "series_name": "Pakistan v West Indies ODI Series", "series_id": 374055, "match_id": 374061, "match_date": "2008-11-16 11:00:00+00:00", "stadium_id": 1965, "stadium_obj_id": 59396, "stadium_name": "Sheikh Zayed Stadium", "stadium_place_id": 977, "stadium_place": "Abu Dhabi", "stadium_country_id": 27, "home_team_id": 7, "home_team_score": "273/6", "home_team_score_info": null, "home_team_innings": 1, "away_team_id": 4, "away_team_score": "242", "away_team_score_info": "46.3/50 ov, target 274", "away_team_innings": 2, "home_team": "Pakistan", "home_team_runs": 273, "home_team_wickets": 6, "home_team_overs_played": 50, "home_team_balls_played": 300, "away_team": "West-Indies", "away_team_runs": 242, "away_team_wickets": 10, "away_team_overs_played": 46.3, "away_team_balls_played": 279}, {"uid": 23044, "odi_type": "daynight", "winner_id": "Pakistan", "status": "Pakistan won by 24 runs", "toss_winner_id": "Pakistan", "toss_choice": "bat", "match_tied": 0, "series_name": "Pakistan v West Indies ODI Series", "series_id": 374055, "match_id": 374060, "match_date": "2008-11-14 11:00:00+00:00", "stadium_id": 1965, "stadium_obj_id": 59396, "stadium_name": "Sheikh Zayed Stadium", "stadium_place_id": 977, "stadium_place": "Abu Dhabi", "stadium_country_id": 27, "home_team_id": 7, "home_team_score": "232", "home_team_score_info": null, "home_team_innings": 1, "away_team_id": 4, "away_team_score": "208", "away_team_score_info": "48.5/50 ov, target 233", "away_team_innings": 2, "home_team": "Pakistan", "home_team_runs": 232, "home_team_wickets": 10, "home_team_overs_played": 49, "home_team_balls_played": 294, "away_team": "West-Indies", "away_team_runs": 208, "away_team_wickets": 10, "away_team_overs_played": 48.5, "away_team_balls_played": 293}, {"uid": 23043, "odi_type": "daynight", "winner_id": "Pakistan", "status": "Pakistan won by 4 wickets (with 1 ball remaining)", "toss_winner_id": "West-Indies", "toss_choice": "bat", "match_tied": 0, "series_name": "Pakistan v West Indies ODI Series", "series_id": 374055, "match_id": 374059, "match_date": "2008-11-12 11:00:00+00:00", "stadium_id": 1965, "stadium_obj_id": 59396, "stadium_name": "Sheikh Zayed Stadium", "stadium_place_id": 977, "stadium_place": "Abu Dhabi", "stadium_country_id": 27, "home_team_id": 4, "home_team_score": "294/9", "home_team_score_info": null, "home_team_innings": 1, "away_team_id": 7, "away_team_score": "295/6", "away_team_score_info": "49.5/50 ov", "away_team_innings": 2, "home_team": "West-Indies", "home_team_runs": 294, "home_team_wickets": 9, "home_team_overs_played": 50, "home_team_balls_played": 300, "away_team": "Pakistan", "away_team_runs": 295, "away_team_wickets": 6, "away_team_overs_played": 49.5, "away_team_balls_played": 299}, {"uid": 20902, "odi_type": "day", "winner_id": "New-Zealand", "status": "New Zealand won by 79 runs", "toss_winner_id": "New-Zealand", "toss_choice": "bat", "match_tied": 0, "series_name": "New Zealand tour of Bangladesh", "series_id": 361750, "match_id": 361757, "match_date": "2008-10-14 03:00:00+00:00", "stadium_id": 1931, "stadium_obj_id": 56658, "stadium_name": "Zahur Ahmed Chowdhury Stadium", "stadium_place_id": 57, "stadium_place": "Chattogram", "stadium_country_id": 25, "home_team_id": 5, "home_team_score": "249/7", "home_team_score_info": null, "home_team_innings": 1, "away_team_id": 25, "away_team_score": "170/8", "away_team_score_info": "50 ov, target 250", "away_team_innings": 2, "home_team": "New-Zealand", "home_team_runs": 249, "home_team_wickets": 7, "home_team_overs_played": 50, "home_team_balls_played": 300, "away_team": "Bangladesh", "away_team_runs": 170, "away_team_wickets": 8, "away_team_overs_played": 50, "away_team_balls_played": 300}, {"uid": 20901, "odi_type": "day", "winner_id": "New-Zealand", "status": "New Zealand won by 75 runs", "toss_winner_id": "Bangladesh", "toss_choice": "bowl", "match_tied": 0, "series_name": "New Zealand tour of Bangladesh", "series_id": 361750, "match_id": 361756, "match_date": "2008-10-11 03:00:00+00:00", "stadium_id": 2025, "stadium_obj_id": 236761, "stadium_name": "Shere Bangla National Stadium", "stadium_place_id": 58, "stadium_place": "Dhaka", "stadium_country_id": 25, "home_team_id": 5, "home_team_score": "212/9", "home_team_score_info": null, "home_team_innings": 1, "away_team_id": 25, "away_team_score": "137", "away_team_score_info": "42.4/50 ov, target 213", "away_team_innings": 2, "home_team": "New-Zealand", "home_team_runs": 212, "home_team_wickets": 9, "home_team_overs_played": 50, "home_team_balls_played": 300, "away_team": "Bangladesh", "away_team_runs": 137, "away_team_wickets": 10, "away_team_overs_played": 42.4, "away_team_balls_played": 256}, {"uid": 20900, "odi_type": "day", "winner_id": "Bangladesh", "status": "Bangladesh won by 7 wickets (with 27 balls remaining)", "toss_winner_id": "Bangladesh", "toss_choice": "bowl", "match_tied": 0, "series_name": "New Zealand tour of Bangladesh", "series_id": 361750, "match_id": 361755, "match_date": "2008-10-09 03:00:00+00:00", "stadium_id": 2025, "stadium_obj_id": 236761, "stadium_name": "Shere Bangla National Stadium", "stadium_place_id": 58, "stadium_place": "Dhaka", "stadium_country_id": 25, "home_team_id": 5, "home_team_score": "201/9", "home_team_score_info": null, "home_team_innings": 1, "away_team_id": 25, "away_team_score": "202/3", "away_team_score_info": "45.3/50 ov", "away_team_innings": 2, "home_team": "New-Zealand", "home_team_runs": 201, "home_team_wickets": 9, "home_team_overs_played": 50, "home_team_balls_played": 300, "away_team": "Bangladesh", "away_team_runs": 202, "away_team_wickets": 3, "away_team_overs_played": 45.3, "away_team_balls_played": 273}, {"uid": 13450, "odi_type": "day", "winner_id": "India", "status": "India won by 7 wickets (with 106 balls remaining)", "toss_winner_id": "India", "toss_choice": "bowl", "match_tied": 0, "series_name": "Commonwealth Bank Series", "series_id": 291340, "match_id": 291369, "match_date": "2008-02-25 23:00:00+00:00", "stadium_id": 905, "stadium_obj_id": 56407, "stadium_name": "Bellerive Oval", "stadium_place_id": 20, "stadium_place": "Hobart", "stadium_country_id": 2, "home_team_id": 8, "home_team_score": "179", "home_team_score_info": null, "home_team_innings": 1, "away_team_id": 6, "away_team_score": "180/3", "away_team_score_info": "32.2/50 ov", "away_team_innings": 2, "home_team": "Sri-Lanka", "home_team_runs": 179, "home_team_wickets": 10, "home_team_overs_played": 47.1, "home_team_balls_played": 283, "away_team": "India", "away_team_runs": 180, "away_team_wickets": 3, "away_team_overs_played": 32.2, "away_team_balls_played": 194}, {"uid": 13447, "odi_type": "daynight", "winner_id": "India", "status": "India won by 2 wickets (with 5 balls remaining)", "toss_winner_id": "Sri-Lanka", "toss_choice": "bat", "match_tied": 0, "series_name": "Commonwealth Bank Series", "series_id": 291340, "match_id": 291366, "match_date": "2008-02-19 03:15:00+00:00", "stadium_id": 131, "stadium_obj_id": 56293, "stadium_name": "Adelaide Oval", "stadium_place_id": 2, "stadium_place": "Adelaide", "stadium_country_id": 2, "home_team_id": 8, "home_team_score": "238/6", "home_team_score_info": null, "home_team_innings": 1, "away_team_id": 6, "away_team_score": "239/8", "away_team_score_info": "49.1/50 ov", "away_team_innings": 2, "home_team": "Sri-Lanka", "home_team_runs": 238, "home_team_wickets": 6, "home_team_overs_played": 50, "home_team_balls_played": 300, "away_team": "India", "away_team_runs": 239, "away_team_wickets": 8, "away_team_overs_played": 49.1, "away_team_balls_played": 295}, {"uid": 13444, "odi_type": "day", "winner_id": "Sri-Lanka", "status": "Sri Lanka won by 8 wickets (with 12 balls remaining) (D/L method)", "toss_winner_id": "Sri-Lanka", "toss_choice": "bowl", "match_tied": 0, "series_name": "Commonwealth Bank Series", "series_id": 291340, "match_id": 291363, "match_date": "2008-02-11 23:00:00+00:00", "stadium_id": 757, "stadium_obj_id": 56370, "stadium_name": "Manuka Oval", "stadium_place_id": 13, "stadium_place": "Canberra", "stadium_country_id": 2, "home_team_id": 6, "home_team_score": "195/5", "home_team_score_info": null, "home_team_innings": 1, "away_team_id": 8, "away_team_score": "154/2", "away_team_score_info": "19/21 ov", "away_team_innings": 2, "home_team": "India", "home_team_runs": 195, "home_team_wickets": 5, "home_team_overs_played": 29, "home_team_balls_played": 174, "away_team": "Sri-Lanka", "away_team_runs": 154, "away_team_wickets": 2, "away_team_overs_played": 19, "away_team_balls_played": 114}, {"uid": 17788, "odi_type": "night", "winner_id": "India", "status": "India won by 7 wickets (with 40 balls remaining)", "toss_winner_id": "Bangladesh", "toss_choice": "bat", "match_tied": 0, "series_name": "Asia Cup", "series_id": 298014, "match_id": 335352, "match_date": "2008-06-28 10:00:00+00:00", "stadium_id": 487, "stadium_obj_id": 58956, "stadium_name": "National Stadium", "stadium_place_id": 867, "stadium_place": "Karachi", "stadium_country_id": 7, "home_team_id": 25, "home_team_score": "283/6", "home_team_score_info": null, "home_team_innings": 1, "away_team_id": 6, "away_team_score": "284/3", "away_team_score_info": "43.2/50 ov", "away_team_innings": 2, "home_team": "Bangladesh", "home_team_runs": 283, "home_team_wickets": 6, "home_team_overs_played": 50, "home_team_balls_played": 300, "away_team": "India", "away_team_runs": 284, "away_team_wickets": 3, "away_team_overs_played": 43.2, "away_team_balls_played": 260}, {"uid": 17787, "odi_type": "night", "winner_id": "India", "status": "India won by 6 wickets (with 47 balls remaining)", "toss_winner_id": "Pakistan", "toss_choice": "bat", "match_tied": 0, "series_name": "Asia Cup", "series_id": 298014, "match_id": 335351, "match_date": "2008-06-26 10:00:00+00:00", "stadium_id": 487, "stadium_obj_id": 58956, "stadium_name": "National Stadium", "stadium_place_id": 867, "stadium_place": "Karachi", "stadium_country_id": 7, "home_team_id": 7, "home_team_score": "299/4", "home_team_score_info": null, "home_team_innings": 1, "away_team_id": 6, "away_team_score": "301/4", "away_team_score_info": "42.1/50 ov, target 300", "away_team_innings": 2, "home_team": "Pakistan", "home_team_runs": 299, "home_team_wickets": 4, "home_team_overs_played": 50, "home_team_balls_played": 300, "away_team": "India", "away_team_runs": 301, "away_team_wickets": 4, "away_team_overs_played": 42.1, "away_team_balls_played": 253}, {"uid": 18160, "odi_type": "daynight", "winner_id": "Pakistan", "status": "Pakistan won by 25 runs", "toss_winner_id": "Pakistan", "toss_choice": "bat", "match_tied": 0, "series_name": "Kitply Cup", "series_id": 345463, "match_id": 345471, "match_date": "2008-06-14 09:00:00+00:00", "stadium_id": 2025, "stadium_obj_id": 236761, "stadium_name": "Shere Bangla National Stadium", "stadium_place_id": 58, "stadium_place": "Dhaka", "stadium_country_id": 25, "home_team_id": 7, "home_team_score": "315/3", "home_team_score_info": null, "home_team_innings": 1, "away_team_id": 6, "away_team_score": "290", "away_team_score_info": "48.2/50 ov, target 316", "away_team_innings": 2, "home_team": "Pakistan", "home_team_runs": 315, "home_team_wickets": 3, "home_team_overs_played": 50, "home_team_balls_played": 300, "away_team": "India", "away_team_runs": 290, "away_team_wickets": 10, "away_team_overs_played": 48.2, "away_team_balls_played": 290}, {"uid": 18159, "odi_type": "daynight", "winner_id": "India", "status": "India won by 7 wickets (with 89 balls remaining)", "toss_winner_id": "Bangladesh", "toss_choice": "bat", "match_tied": 0, "series_name": "Kitply Cup", "series_id": 345463, "match_id": 345470, "match_date": "2008-06-12 09:00:00+00:00", "stadium_id": 2025, "stadium_obj_id": 236761, "stadium_name": "Shere Bangla National Stadium", "stadium_place_id": 58, "stadium_place": "Dhaka", "stadium_country_id": 25, "home_team_id": 25, "home_team_score": "222", "home_team_score_info": null, "home_team_innings": 1, "away_team_id": 6, "away_team_score": "223/3", "away_team_score_info": "35.1/50 ov", "away_team_innings": 2, "home_team": "Bangladesh", "home_team_runs": 222, "home_team_wickets": 10, "home_team_overs_played": 49.5, "home_team_balls_played": 299, "away_team": "India", "away_team_runs": 223, "away_team_wickets": 3, "away_team_overs_played": 35.1, "away_team_balls_played": 211}, {"uid": 18158, "odi_type": "daynight", "winner_id": "India", "status": "India won by 140 runs", "toss_winner_id": "India", "toss_choice": "bat", "match_tied": 0, "series_name": "Kitply Cup", "series_id": 345463, "match_id": 345469, "match_date": "2008-06-10 09:00:00+00:00", "stadium_id": 2025, "stadium_obj_id": 236761, "stadium_name": "Shere Bangla National Stadium", "stadium_place_id": 58, "stadium_place": "Dhaka", "stadium_country_id": 25, "home_team_id": 6, "home_team_score": "330/8", "home_team_score_info": null, "home_team_innings": 1, "away_team_id": 7, "away_team_score": "190", "away_team_score_info": "35.4/50 ov, target 331", "away_team_innings": 2, "home_team": "India", "home_team_runs": 330, "home_team_wickets": 8, "home_team_overs_played": 50, "home_team_balls_played": 300, "away_team": "Pakistan", "away_team_runs": 190, "away_team_wickets": 10, "away_team_overs_played": 35.4, "away_team_balls_played": 214}, {"uid": 17794, "odi_type": "night", "winner_id": "Sri-Lanka", "status": "Sri Lanka won by 100 runs", "toss_winner_id": "India", "toss_choice": "bowl", "match_tied": 0, "series_name": "Asia Cup", "series_id": 298014, "match_id": 335358, "match_date": "2008-07-06 10:00:00+00:00", "stadium_id": 487, "stadium_obj_id": 58956, "stadium_name": "National Stadium", "stadium_place_id": 867, "stadium_place": "Karachi", "stadium_country_id": 7, "home_team_id": 8, "home_team_score": "273", "home_team_score_info": null, "home_team_innings": 1, "away_team_id": 6, "away_team_score": "173", "away_team_score_info": "39.3/50 ov, target 274", "away_team_innings": 2, "home_team": "Sri-Lanka", "home_team_runs": 273, "home_team_wickets": 10, "home_team_overs_played": 49.5, "home_team_balls_played": 299, "away_team": "India", "away_team_runs": 173, "away_team_wickets": 10, "away_team_overs_played": 39.3, "away_team_balls_played": 237}, {"uid": 17792, "odi_type": "night", "winner_id": "India", "status": "India won by 6 wickets (with 19 balls remaining)", "toss_winner_id": "Sri-Lanka", "toss_choice": "bat", "match_tied": 0, "series_name": "Asia Cup", "series_id": 298014, "match_id": 335356, "match_date": "2008-07-03 10:00:00+00:00", "stadium_id": 487, "stadium_obj_id": 58956, "stadium_name": "National Stadium", "stadium_place_id": 867, "stadium_place": "Karachi", "stadium_country_id": 7, "home_team_id": 8, "home_team_score": "308/8", "home_team_score_info": null, "home_team_innings": 1, "away_team_id": 6, "away_team_score": "310/4", "away_team_score_info": "46.5/50 ov, target 309", "away_team_innings": 2, "home_team": "Sri-Lanka", "home_team_runs": 308, "home_team_wickets": 8, "home_team_overs_played": 50, "home_team_balls_played": 300, "away_team": "India", "away_team_runs": 310, "away_team_wickets": 4, "away_team_overs_played": 46.5, "away_team_balls_played": 281}, {"uid": 17791, "odi_type": "night", "winner_id": "Pakistan", "status": "Pakistan won by 8 wickets (with 27 balls remaining)", "toss_winner_id": "India", "toss_choice": "bat", "match_tied": 0, "series_name": "Asia Cup", "series_id": 298014, "match_id": 335355, "match_date": "2008-07-02 10:00:00+00:00", "stadium_id": 487, "stadium_obj_id": 58956, "stadium_name": "National Stadium", "stadium_place_id": 867, "stadium_place": "Karachi", "stadium_country_id": 7, "home_team_id": 6, "home_team_score": "308/7", "home_team_score_info": null, "home_team_innings": 1, "away_team_id": 7, "away_team_score": "309/2", "away_team_score_info": "45.3/50 ov", "away_team_innings": 2, "home_team": "India", "home_team_runs": 308, "home_team_wickets": 7, "home_team_overs_played": 50, "home_team_balls_played": 300, "away_team": "Pakistan", "away_team_runs": 309, "away_team_wickets": 2, "away_team_overs_played": 45.3, "away_team_balls_played": 273}, {"uid": 18121, "odi_type": "daynight", "winner_id": "Sri-Lanka", "status": "Sri Lanka won by 112 runs (D/L method)", "toss_winner_id": "Sri-Lanka", "toss_choice": "bat", "match_tied": 0, "series_name": "India tour of Sri Lanka", "series_id": 343726, "match_id": 343736, "match_date": "2008-08-29 09:00:00+00:00", "stadium_id": 1004, "stadium_obj_id": 59306, "stadium_name": "R.Premadasa Stadium", "stadium_place_id": 955, "stadium_place": "Colombo", "stadium_country_id": 8, "home_team_id": 8, "home_team_score": "227/6", "home_team_score_info": null, "home_team_innings": 1, "away_team_id": 6, "away_team_score": "103", "away_team_score_info": "26.3/44 ov, target 216", "away_team_innings": 2, "home_team": "Sri-Lanka", "home_team_runs": 227, "home_team_wickets": 6, "home_team_overs_played": 50, "home_team_balls_played": 300, "away_team": "India", "away_team_runs": 103, "away_team_wickets": 10, "away_team_overs_played": 26.3, "away_team_balls_played": 159}, {"uid": 21066, "odi_type": "daynight", "winner_id": "India", "status": "India won by 46 runs", "toss_winner_id": "India", "toss_choice": "bat", "match_tied": 0, "series_name": "India tour of Sri Lanka", "series_id": 343726, "match_id": 366341, "match_date": "2008-08-27 09:00:00+00:00", "stadium_id": 1004, "stadium_obj_id": 59306, "stadium_name": "R.Premadasa Stadium", "stadium_place_id": 955, "stadium_place": "Colombo", "stadium_country_id": 8, "home_team_id": 6, "home_team_score": "258", "home_team_score_info": null, "home_team_innings": 1, "away_team_id": 8, "away_team_score": "212", "away_team_score_info": "46.3/50 ov, target 259", "away_team_innings": 2, "home_team": "India", "home_team_runs": 258, "home_team_wickets": 10, "home_team_overs_played": 49.4, "home_team_balls_played": 298, "away_team": "Sri-Lanka", "away_team_runs": 212, "away_team_wickets": 10, "away_team_overs_played": 46.3, "away_team_balls_played": 279}, {"uid": 18119, "odi_type": "daynight", "winner_id": "India", "status": "India won by 33 runs", "toss_winner_id": "India", "toss_choice": "bat", "match_tied": 0, "series_name": "India tour of Sri Lanka", "series_id": 343726, "match_id": 343734, "match_date": "2008-08-24 09:00:00+00:00", "stadium_id": 1004, "stadium_obj_id": 59306, "stadium_name": "R.Premadasa Stadium", "stadium_place_id": 955, "stadium_place": "Colombo", "stadium_country_id": 8, "home_team_id": 6, "home_team_score": "237/9", "home_team_score_info": null, "home_team_innings": 1, "away_team_id": 8, "away_team_score": "204", "away_team_score_info": "49/50 ov, target 238", "away_team_innings": 2, "home_team": "India", "home_team_runs": 237, "home_team_wickets": 9, "home_team_overs_played": 50, "home_team_balls_played": 300, "away_team": "Sri-Lanka", "away_team_runs": 204, "away_team_wickets": 10, "away_team_overs_played": 49, "away_team_balls_played": 294}, {"uid": 18118, "odi_type": "day", "winner_id": "India", "status": "India won by 3 wickets (with 62 balls remaining)", "toss_winner_id": "India", "toss_choice": "bowl", "match_tied": 0, "series_name": "India tour of Sri Lanka", "series_id": 343726, "match_id": 343733, "match_date": "2008-08-20 04:30:00+00:00", "stadium_id": 1434, "stadium_obj_id": 59368, "stadium_name": "Rangiri Dambulla International Stadium", "stadium_place_id": 967, "stadium_place": "Dambulla", "stadium_country_id": 8, "home_team_id": 8, "home_team_score": "142", "home_team_score_info": null, "home_team_innings": 1, "away_team_id": 6, "away_team_score": "143/7", "away_team_score_info": "39.4/50 ov", "away_team_innings": 2, "home_team": "Sri-Lanka", "home_team_runs": 142, "home_team_wickets": 10, "home_team_overs_played": 38.3, "home_team_balls_played": 231, "away_team": "India", "away_team_runs": 143, "away_team_wickets": 7, "away_team_overs_played": 39.4, "away_team_balls_played": 238}, {"uid": 18117, "odi_type": "day", "winner_id": "Sri-Lanka", "status": "Sri Lanka won by 8 wickets (with 91 balls remaining)", "toss_winner_id": "India", "toss_choice": "bat", "match_tied": 0, "series_name": "India tour of Sri Lanka", "series_id": 343726, "match_id": 343732, "match_date": "2008-08-18 04:30:00+00:00", "stadium_id": 1434, "stadium_obj_id": 59368, "stadium_name": "Rangiri Dambulla International Stadium", "stadium_place_id": 967, "stadium_place": "Dambulla", "stadium_country_id": 8, "home_team_id": 6, "home_team_score": "146", "home_team_score_info": null, "home_team_innings": 1, "away_team_id": 8, "away_team_score": "147/2", "away_team_score_info": "34.5/50 ov", "away_team_innings": 2, "home_team": "India", "home_team_runs": 146, "home_team_wickets": 10, "home_team_overs_played": 46, "home_team_balls_played": 276, "away_team": "Sri-Lanka", "away_team_runs": 147, "away_team_wickets": 2, "away_team_overs_played": 34.5, "away_team_balls_played": 209}, {"uid": 18126, "odi_type": "daynight", "winner_id": "Pakistan", "status": "Pakistan won by 150 runs", "toss_winner_id": "Pakistan", "toss_choice": "bat", "match_tied": 0, "series_name": "Bangladesh tour of Pakistan", "series_id": 343065, "match_id": 343763, "match_date": "2008-04-19 10:00:00+00:00", "stadium_id": 487, "stadium_obj_id": 58956, "stadium_name": "National Stadium", "stadium_place_id": 867, "stadium_place": "Karachi", "stadium_country_id": 7, "home_team_id": 7, "home_team_score": "329/9", "home_team_score_info": null, "home_team_innings": 1, "away_team_id": 25, "away_team_score": "179", "away_team_score_info": "40.5/50 ov, target 330", "away_team_innings": 2, "home_team": "Pakistan", "home_team_runs": 329, "home_team_wickets": 9, "home_team_overs_played": 50, "home_team_balls_played": 300, "away_team": "Bangladesh", "away_team_runs": 179, "away_team_wickets": 10, "away_team_overs_played": 40.5, "away_team_balls_played": 245}, {"uid": 18125, "odi_type": "daynight", "winner_id": "Pakistan", "status": "Pakistan won by 7 wickets (with 33 balls remaining)", "toss_winner_id": "Bangladesh", "toss_choice": "bat", "match_tied": 0, "series_name": "Bangladesh tour of Pakistan", "series_id": 343065, "match_id": 343762, "match_date": "2008-04-16 10:00:00+00:00", "stadium_id": 1597, "stadium_obj_id": 58986, "stadium_name": "Multan Cricket Stadium", "stadium_place_id": 870, "stadium_place": "Multan", "stadium_country_id": 7, "home_team_id": 25, "home_team_score": "210", "home_team_score_info": null, "home_team_innings": 1, "away_team_id": 7, "away_team_score": "212/3", "away_team_score_info": "44.3/50 ov, target 211", "away_team_innings": 2, "home_team": "Bangladesh", "home_team_runs": 210, "home_team_wickets": 10, "home_team_overs_played": 49.1, "home_team_balls_played": 295, "away_team": "Pakistan", "away_team_runs": 212, "away_team_wickets": 3, "away_team_overs_played": 44.3, "away_team_balls_played": 267}, {"uid": 18124, "odi_type": "daynight", "winner_id": "Pakistan", "status": "Pakistan won by 23 runs", "toss_winner_id": "Pakistan", "toss_choice": "bat", "match_tied": 0, "series_name": "Bangladesh tour of Pakistan", "series_id": 343065, "match_id": 343761, "match_date": "2008-04-13 10:00:00+00:00", "stadium_id": 545, "stadium_obj_id": 58967, "stadium_name": "Gaddafi Stadium", "stadium_place_id": 868, "stadium_place": "Lahore", "stadium_country_id": 7, "home_team_id": 7, "home_team_score": "308/8", "home_team_score_info": null, "home_team_innings": 1, "away_team_id": 25, "away_team_score": "285/7", "away_team_score_info": "50 ov, target 309", "away_team_innings": 2, "home_team": "Pakistan", "home_team_runs": 308, "home_team_wickets": 8, "home_team_overs_played": 50, "home_team_balls_played": 300, "away_team": "Bangladesh", "away_team_runs": 285, "away_team_wickets": 7, "away_team_overs_played": 50, "away_team_balls_played": 300}, {"uid": 18123, "odi_type": "daynight", "winner_id": "Pakistan", "status": "Pakistan won by 7 wickets (with 10 balls remaining) (D/L method)", "toss_winner_id": "Bangladesh", "toss_choice": "bat", "match_tied": 0, "series_name": "Bangladesh tour of Pakistan", "series_id": 343065, "match_id": 343760, "match_date": "2008-04-11 10:00:00+00:00", "stadium_id": 639, "stadium_obj_id": 58927, "stadium_name": "Iqbal Stadium", "stadium_place_id": 863, "stadium_place": "Faisalabad", "stadium_country_id": 7, "home_team_id": 25, "home_team_score": "225/8", "home_team_score_info": null, "home_team_innings": 1, "away_team_id": 7, "away_team_score": "160/3", "away_team_score_info": "23.2/25 ov, target 158", "away_team_innings": 2, "home_team": "Bangladesh", "home_team_runs": 225, "home_team_wickets": 8, "home_team_overs_played": 48.2, "home_team_balls_played": 290, "away_team": "Pakistan", "away_team_runs": 160, "away_team_wickets": 3, "away_team_overs_played": 23.2, "away_team_balls_played": 140}, {"uid": 18122, "odi_type": "daynight", "winner_id": "Pakistan", "status": "Pakistan won by 152 runs (D/L method)", "toss_winner_id": "Pakistan", "toss_choice": "bat", "match_tied": 0, "series_name": "Bangladesh tour of Pakistan", "series_id": 343065, "match_id": 343759, "match_date": "2008-04-08 10:00:00+00:00", "stadium_id": 545, "stadium_obj_id": 58967, "stadium_name": "Gaddafi Stadium", "stadium_place_id": 868, "stadium_place": "Lahore", "stadium_country_id": 7, "home_team_id": 7, "home_team_score": "322/5", "home_team_score_info": null, "home_team_innings": 1, "away_team_id": 25, "away_team_score": "129", "away_team_score_info": "29.5/39 ov, target 282", "away_team_innings": 2, "home_team": "Pakistan", "home_team_runs": 322, "home_team_wickets": 5, "home_team_overs_played": 50, "home_team_balls_played": 300, "away_team": "Bangladesh", "away_team_runs": 129, "away_team_wickets": 10, "away_team_overs_played": 29.5, "away_team_balls_played": 179}, {"uid": 17789, "odi_type": "night", "winner_id": "Sri-Lanka", "status": "Sri Lanka won by 64 runs", "toss_winner_id": "Pakistan", "toss_choice": "bowl", "match_tied": 0, "series_name": "Asia Cup", "series_id": 298014, "match_id": 335353, "match_date": "2008-06-29 10:00:00+00:00", "stadium_id": 487, "stadium_obj_id": 58956, "stadium_name": "National Stadium", "stadium_place_id": 867, "stadium_place": "Karachi", "stadium_country_id": 7, "home_team_id": 8, "home_team_score": "302/7", "home_team_score_info": null, "home_team_innings": 1, "away_team_id": 7, "away_team_score": "238/9", "away_team_score_info": "50 ov, target 303", "away_team_innings": 2, "home_team": "Sri-Lanka", "home_team_runs": 302, "home_team_wickets": 7, "home_team_overs_played": 50, "home_team_balls_played": 300, "away_team": "Pakistan", "away_team_runs": 238, "away_team_wickets": 9, "away_team_overs_played": 50, "away_team_balls_played": 300}, {"uid": 18157, "odi_type": "daynight", "winner_id": "Pakistan", "status": "Pakistan won by 70 runs", "toss_winner_id": "Bangladesh", "toss_choice": "bowl", "match_tied": 0, "series_name": "Kitply Cup", "series_id": 345463, "match_id": 345468, "match_date": "2008-06-08 09:00:00+00:00", "stadium_id": 2025, "stadium_obj_id": 236761, "stadium_name": "Shere Bangla National Stadium", "stadium_place_id": 58, "stadium_place": "Dhaka", "stadium_country_id": 25, "home_team_id": 7, "home_team_score": "233", "home_team_score_info": null, "home_team_innings": 1, "away_team_id": 25, "away_team_score": "163/8", "away_team_score_info": "40/40 ov, target 234", "away_team_innings": 2, "home_team": "Pakistan", "home_team_runs": 233, "home_team_wickets": 10, "home_team_overs_played": 39.3, "home_team_balls_played": 237, "away_team": "Bangladesh", "away_team_runs": 163, "away_team_wickets": 8, "away_team_overs_played": 40, "away_team_balls_played": 240}, {"uid": 17793, "odi_type": "night", "winner_id": "Pakistan", "status": "Pakistan won by 10 wickets (with 182 balls remaining)", "toss_winner_id": "Bangladesh", "toss_choice": "bat", "match_tied": 0, "series_name": "Asia Cup", "series_id": 298014, "match_id": 335357, "match_date": "2008-07-04 10:00:00+00:00", "stadium_id": 487, "stadium_obj_id": 58956, "stadium_name": "National Stadium", "stadium_place_id": 867, "stadium_place": "Karachi", "stadium_country_id": 7, "home_team_id": 25, "home_team_score": "115", "home_team_score_info": null, "home_team_innings": 1, "away_team_id": 7, "away_team_score": "116/0", "away_team_score_info": "19.4/50 ov", "away_team_innings": 2, "home_team": "Bangladesh", "home_team_runs": 115, "home_team_wickets": 10, "home_team_overs_played": 38.2, "home_team_balls_played": 230, "away_team": "Pakistan", "away_team_runs": 116, "away_team_wickets": 0, "away_team_overs_played": 19.4, "away_team_balls_played": 118}, {"uid": 17790, "odi_type": "night", "winner_id": "Sri-Lanka", "status": "Sri Lanka won by 158 runs", "toss_winner_id": "Sri-Lanka", "toss_choice": "bat", "match_tied": 0, "series_name": "Asia Cup", "series_id": 298014, "match_id": 335354, "match_date": "2008-06-30 10:00:00+00:00", "stadium_id": 487, "stadium_obj_id": 58956, "stadium_name": "National Stadium", "stadium_place_id": 867, "stadium_place": "Karachi", "stadium_country_id": 7, "home_team_id": 8, "home_team_score": "332/8", "home_team_score_info": null, "home_team_innings": 1, "away_team_id": 25, "away_team_score": "174", "away_team_score_info": "38.3/50 ov, target 333", "away_team_innings": 2, "home_team": "Sri-Lanka", "home_team_runs": 332, "home_team_wickets": 8, "home_team_overs_played": 50, "home_team_balls_played": 300, "away_team": "Bangladesh", "away_team_runs": 174, "away_team_wickets": 10, "away_team_overs_played": 38.3, "away_team_balls_played": 231}, {"uid": 17784, "odi_type": "night", "winner_id": "Sri-Lanka", "status": "Sri Lanka won by 131 runs", "toss_winner_id": "Bangladesh", "toss_choice": "bowl", "match_tied": 0, "series_name": "Asia Cup", "series_id": 298014, "match_id": 335348, "match_date": "2008-06-25 10:00:00+00:00", "stadium_id": 545, "stadium_obj_id": 58967, "stadium_name": "Gaddafi Stadium", "stadium_place_id": 868, "stadium_place": "Lahore", "stadium_country_id": 7, "home_team_id": 8, "home_team_score": "357/9", "home_team_score_info": null, "home_team_innings": 1, "away_team_id": 25, "away_team_score": "226/7", "away_team_score_info": "50 ov, target 358", "away_team_innings": 2, "home_team": "Sri-Lanka", "home_team_runs": 357, "home_team_wickets": 9, "home_team_overs_played": 50, "home_team_balls_played": 300, "away_team": "Bangladesh", "away_team_runs": 226, "away_team_wickets": 7, "away_team_overs_played": 50, "away_team_balls_played": 300}]